<?xml version="1.0" encoding="utf-8" standalone="no"?><level><name>custom/novy level</name><timeLimit>0</timeLimit><rooms><room><index>0</index><width>10.0</width><height>10.0</height><position>(12.733518, 0.10000038, 4.406292)</position><isAloved>true</isAloved><neighbours/></room><room><index>1</index><width>10.0</width><height>10.0</height><position>(32.894085, 0.10000229, 4.332926)</position><isAloved>false</isAloved><neighbours><neighbour>2</neighbour></neighbours></room><room><index>2</index><width>10.0</width><height>10.0</height><position>(32.90001, 0.10000038, 24.416681)</position><isAloved>true</isAloved><neighbours><neighbour>1</neighbour><neighbour>3</neighbour><neighbour>4</neighbour></neighbours></room><room><index>3</index><width>10.0</width><height>10.0</height><position>(12.739992, 0.10000229, 24.467009)</position><item>FLASH</item><isAloved>true</isAloved><neighbours><neighbour>2</neighbour></neighbours></room><room><index>4</index><width>10.0</width><height>10.0</height><position>(21.94328, 0.09999657, 45.580956)</position><isAloved>true</isAloved><neighbours><neighbour>2</neighbour></neighbours></room></rooms><start>0</start><finish>2</finish><avalibleObst/></level>